{"기념일": ["세계 달의 날", "한여름의 시작 날", "장마철 끝나는 시기", "절기 토왕 용사의 날", "키스의 날 (일본)", "러브 레터의 날 (일본)", "햄버거의 날 (일본)", "월면 착륙의 날", "당구의 날 (일본)"], "사건": {"1913년": "JR 도카이 미노부선이 개업했다.", "1929년": "소련군이 만주 수분하를 공격하면서 봉소전쟁 시작.", "1944년": "히틀러 암살 미수사건이 일어났다.", "1950년": "6.25 전쟁 중 북한군이 대전을 함락시켰다. 그 무렵 중국은 만주 일대에 대규모 병력을 배치하고 있었다.", "1967년": "7.20 사건 발생.", "1969년": "아폴로 11호로 인류 첫 달 착륙이 이루어졌다.", "1992년": "수인선 협궤열차의 운행 구간 중 남인천-송도 구간에 이어 송도-소래 구간이 폐지되면서 잔여 구간은 소래-수원.", "1996년": "1995년 제정하고, 1996년 부터", "1997년": "보름달하고 해왕성 행성합. 14시 34분 황위 차이 = 3746°", "2006년": "거북이 가수가 부른 비행기가 이날 발매되었다", "2011년": "루돌프 헤스의 무덤이 철거되었으며 유해는 인근 호수에 뿌려졌다. 네오 나치들이 참배하러 오는 것을 막을 수 없었기 때문이라고.", "2014년": "지박소년 하나코군 애니하고, 관련된 날짜 이다", "2016년": ["신비아파트 : 고스트볼의 비밀 첫 방송일 이때부터 인기작이 되어서 현재까지 계속 시리즈가 나왔다", "오후 5시 45분 오버워치 한국서버가 처음으로 터졌다.", "또 다시 KBO 리그에서 승부조작 의혹이 발생했다."]}}